feanorTempDir/__init__.py
feanorTempDir/temp.py
feanorTempDir-1.0.0.dist-info/METADATA
feanorTempDir-1.0.0.dist-info/WHEEL
feanorTempDir-1.0.0.dist-info/top_level.txt
feanorTempDir-1.0.0.dist-info/RECORD
